{"moduleCode":"DEATH","children":[{"name":"ANGUL","distCode":"ORAN","children":[{"name":"Deaths Registered","value":7785,"size":7785},{"name":"Death Certificates Applied","value":4323,"size":4323},{"name":"Death Certificates Issued","value":4489,"size":4489}]},{"name":"BALANGIR","distCode":"ORBL","children":[{"name":"Deaths Registered","value":12187,"size":12187},{"name":"Death Certificates Applied","value":6124,"size":6124},{"name":"Death Certificates Issued","value":6167,"size":6167}]},{"name":"BALASORE","distCode":"ORBW","children":[{"name":"Deaths Registered","value":9849,"size":9849},{"name":"Death Certificates Applied","value":5765,"size":5765},{"name":"Death Certificates Issued","value":5472,"size":5472}]},{"name":"BARGARH","distCode":"ORBR","children":[{"name":"Deaths Registered","value":11581,"size":11581},{"name":"Death Certificates Applied","value":6406,"size":6406},{"name":"Death Certificates Issued","value":6184,"size":6184}]},{"name":"BHADRAK","distCode":"ORBH","children":[{"name":"Deaths Registered","value":5261,"size":5261},{"name":"Death Certificates Applied","value":3221,"size":3221},{"name":"Death Certificates Issued","value":3105,"size":3105}]},{"name":"BOUDH","distCode":"ORBD","children":[{"name":"Deaths Registered","value":3223,"size":3223},{"name":"Death Certificates Applied","value":1690,"size":1690},{"name":"Death Certificates Issued","value":1652,"size":1652}]},{"name":"CUTTACK","distCode":"ORCU","children":[{"name":"Deaths Registered","value":11571,"size":11571},{"name":"Death Certificates Applied","value":6126,"size":6126},{"name":"Death Certificates Issued","value":6030,"size":6030}]},{"name":"DEOGARH","distCode":"ORDE","children":[{"name":"Deaths Registered","value":2170,"size":2170},{"name":"Death Certificates Applied","value":1020,"size":1020},{"name":"Death Certificates Issued","value":1110,"size":1110}]},{"name":"DHENKANAL","distCode":"ORDH","children":[{"name":"Deaths Registered","value":6633,"size":6633},{"name":"Death Certificates Applied","value":3133,"size":3133},{"name":"Death Certificates Issued","value":3084,"size":3084}]},{"name":"GAJAPATI","distCode":"ORGP","children":[{"name":"Deaths Registered","value":3959,"size":3959},{"name":"Death Certificates Applied","value":2339,"size":2339},{"name":"Death Certificates Issued","value":2239,"size":2239}]},{"name":"GANJAM","distCode":"ORGN","children":[{"name":"Deaths Registered","value":21017,"size":21017},{"name":"Death Certificates Applied","value":13626,"size":13626},{"name":"Death Certificates Issued","value":13716,"size":13716}]},{"name":"JAGATSINGHPUR","distCode":"ORJS","children":[{"name":"Deaths Registered","value":6893,"size":6893},{"name":"Death Certificates Applied","value":3945,"size":3945},{"name":"Death Certificates Issued","value":3890,"size":3890}]},{"name":"JAJPUR","distCode":"ORJP","children":[{"name":"Deaths Registered","value":10752,"size":10752},{"name":"Death Certificates Applied","value":6422,"size":6422},{"name":"Death Certificates Issued","value":6264,"size":6264}]},{"name":"JHARSUGUDA","distCode":"ORJH","children":[{"name":"Deaths Registered","value":2748,"size":2748},{"name":"Death Certificates Applied","value":1472,"size":1472},{"name":"Death Certificates Issued","value":1441,"size":1441}]},{"name":"KALAHANDI","distCode":"ORKL","children":[{"name":"Deaths Registered","value":11396,"size":11396},{"name":"Death Certificates Applied","value":5600,"size":5600},{"name":"Death Certificates Issued","value":5427,"size":5427}]},{"name":"KANDHAMAL","distCode":"ORKN","children":[{"name":"Deaths Registered","value":3776,"size":3776},{"name":"Death Certificates Applied","value":1761,"size":1761},{"name":"Death Certificates Issued","value":1573,"size":1573}]},{"name":"KENDRAPARA","distCode":"ORKP","children":[{"name":"Deaths Registered","value":9719,"size":9719},{"name":"Death Certificates Applied","value":6344,"size":6344},{"name":"Death Certificates Issued","value":6306,"size":6306}]},{"name":"KEONJHAR","distCode":"ORKJ","children":[{"name":"Deaths Registered","value":10268,"size":10268},{"name":"Death Certificates Applied","value":4015,"size":4015},{"name":"Death Certificates Issued","value":4106,"size":4106}]},{"name":"KHORDHA","distCode":"ORKH","children":[{"name":"Deaths Registered","value":7620,"size":7620},{"name":"Death Certificates Applied","value":4648,"size":4648},{"name":"Death Certificates Issued","value":4474,"size":4474}]},{"name":"KORAPUT","distCode":"ORKO","children":[{"name":"Deaths Registered","value":7396,"size":7396},{"name":"Death Certificates Applied","value":2718,"size":2718},{"name":"Death Certificates Issued","value":2539,"size":2539}]},{"name":"MALKANGIRI","distCode":"ORML","children":[{"name":"Deaths Registered","value":4247,"size":4247},{"name":"Death Certificates Applied","value":1584,"size":1584},{"name":"Death Certificates Issued","value":1544,"size":1544}]},{"name":"MAYURBHANJ","distCode":"ORMY","children":[{"name":"Deaths Registered","value":16170,"size":16170},{"name":"Death Certificates Applied","value":6922,"size":6922},{"name":"Death Certificates Issued","value":6629,"size":6629}]},{"name":"NABARANGPUR","distCode":"ORNB","children":[{"name":"Deaths Registered","value":6933,"size":6933},{"name":"Death Certificates Applied","value":2273,"size":2273},{"name":"Death Certificates Issued","value":2162,"size":2162}]},{"name":"NAYAGARH","distCode":"ORNY","children":[{"name":"Deaths Registered","value":5673,"size":5673},{"name":"Death Certificates Applied","value":3604,"size":3604},{"name":"Death Certificates Issued","value":3446,"size":3446}]},{"name":"NUAPADA","distCode":"ORNU","children":[{"name":"Deaths Registered","value":4966,"size":4966},{"name":"Death Certificates Applied","value":2225,"size":2225},{"name":"Death Certificates Issued","value":2213,"size":2213}]},{"name":"PURI","distCode":"ORPU","children":[{"name":"Deaths Registered","value":7773,"size":7773},{"name":"Death Certificates Applied","value":4773,"size":4773},{"name":"Death Certificates Issued","value":4635,"size":4635}]},{"name":"RAYAGADA","distCode":"ORRA","children":[{"name":"Deaths Registered","value":5849,"size":5849},{"name":"Death Certificates Applied","value":2329,"size":2329},{"name":"Death Certificates Issued","value":2339,"size":2339}]},{"name":"SAMBALPUR","distCode":"ORSA","children":[{"name":"Deaths Registered","value":5626,"size":5626},{"name":"Death Certificates Applied","value":2810,"size":2810},{"name":"Death Certificates Issued","value":2743,"size":2743}]},{"name":"SUBARNAPUR","distCode":"ORSO","children":[{"name":"Deaths Registered","value":3590,"size":3590},{"name":"Death Certificates Applied","value":1711,"size":1711},{"name":"Death Certificates Issued","value":1672,"size":1672}]},{"name":"SUNDARGARH","distCode":"ORSU","children":[{"name":"Deaths Registered","value":10660,"size":10660},{"name":"Death Certificates Applied","value":5188,"size":5188},{"name":"Death Certificates Issued","value":5104,"size":5104}]}]}